setup.cfg
setup.py
least_asymmetry/__init__.py
least_asymmetry/asym.py
least_asymmetry/make_asym.cc
least_asymmetry.egg-info/PKG-INFO
least_asymmetry.egg-info/SOURCES.txt
least_asymmetry.egg-info/dependency_links.txt
least_asymmetry.egg-info/not-zip-safe
least_asymmetry.egg-info/top_level.txt
least_asymmetry/include/pybind11/attr.h
least_asymmetry/include/pybind11/cast.h
least_asymmetry/include/pybind11/common.h
least_asymmetry/include/pybind11/complex.h
least_asymmetry/include/pybind11/descr.h
least_asymmetry/include/pybind11/eigen.h
least_asymmetry/include/pybind11/eval.h
least_asymmetry/include/pybind11/functional.h
least_asymmetry/include/pybind11/numpy.h
least_asymmetry/include/pybind11/operators.h
least_asymmetry/include/pybind11/pybind11.h
least_asymmetry/include/pybind11/pytypes.h
least_asymmetry/include/pybind11/stl.h
least_asymmetry/include/pybind11/stl_bind.h
least_asymmetry/include/pybind11/typeid.h