Metadata-Version: 1.1
Name: least-asymmetry
Version: 0.40
Summary: A module for calculating centers though least asymmetry
Home-page: https://github.com/natelust/least_asymmetry
Author: Nate Lust
Author-email: nlust@astro.princeton.edu
License: UNKNOWN
Download-URL: https://github.com/natelust/least_asymmetry/archive/0.40.tar.gz
Keywords: astronomy,centering,astrophysics,centroid,least asymmetry
Platform: UNKNOWN
